oarepo_c4gh/__init__.py
oarepo_c4gh/exceptions.py
oarepo_c4gh/crypt4gh/__init__.py
oarepo_c4gh/crypt4gh/analyzer.py
oarepo_c4gh/crypt4gh/crypt4gh.py
oarepo_c4gh/crypt4gh/dek.py
oarepo_c4gh/crypt4gh/dek_collection.py
oarepo_c4gh/crypt4gh/rawio.py
oarepo_c4gh/crypt4gh/util.py
oarepo_c4gh/crypt4gh/writer.py
oarepo_c4gh/crypt4gh/common/__init__.py
oarepo_c4gh/crypt4gh/common/data_block.py
oarepo_c4gh/crypt4gh/common/header.py
oarepo_c4gh/crypt4gh/common/header_packet.py
oarepo_c4gh/crypt4gh/common/proto4gh.py
oarepo_c4gh/crypt4gh/filter/__init__.py
oarepo_c4gh/crypt4gh/filter/add_recipient.py
oarepo_c4gh/crypt4gh/filter/add_recipient_header.py
oarepo_c4gh/crypt4gh/filter/filter.py
oarepo_c4gh/crypt4gh/filter/header.py
oarepo_c4gh/crypt4gh/filter/only_readable.py
oarepo_c4gh/crypt4gh/filter/only_readable_header.py
oarepo_c4gh/crypt4gh/stream/__init__.py
oarepo_c4gh/crypt4gh/stream/header.py
oarepo_c4gh/crypt4gh/stream/header_packet.py
oarepo_c4gh/crypt4gh/stream/stream4gh.py
oarepo_c4gh/key/__init__.py
oarepo_c4gh/key/c4gh.py
oarepo_c4gh/key/external.py
oarepo_c4gh/key/external_software.py
oarepo_c4gh/key/gpg_agent.py
oarepo_c4gh/key/http.py
oarepo_c4gh/key/http_path_key_server.py
oarepo_c4gh/key/key.py
oarepo_c4gh/key/key_collection.py
oarepo_c4gh/key/software.py
oarepo_c4gh/key/writer.py
oarepo_c4gh-0.13.1.dist-info/licenses/LICENSE
oarepo_c4gh-0.13.1.dist-info/METADATA
oarepo_c4gh-0.13.1.dist-info/WHEEL
oarepo_c4gh-0.13.1.dist-info/top_level.txt
oarepo_c4gh-0.13.1.dist-info/RECORD
