Metadata-Version: 2.4
Name: oarepo_c4gh
Version: 0.13.1
Author-email: Dominik Pantůček <dominik.pantucek@trustica.cz>
Project-URL: Homepage, https://github.com/oarepo/oarepo-c4gh
Project-URL: Issues, https://github.com/oarepo/oarepo-c4gh/issues
Classifier: Programming Language :: Python :: 3
Classifier: License :: OSI Approved :: MIT License
Classifier: Operating System :: OS Independent
Requires-Python: >=3.12
License-File: LICENSE
Requires-Dist: pynacl>=1.5.0
Requires-Dist: bcrypt
Requires-Dist: cryptography
Provides-Extra: dev
Requires-Dist: mkdocstrings[python]>=0.18; extra == "dev"
Requires-Dist: mkdocs-material; extra == "dev"
Requires-Dist: pytest; extra == "dev"
Requires-Dist: pytest-cov; extra == "dev"
Requires-Dist: types-uwsgi>=2.0.0.20250809; extra == "dev"
Dynamic: license-file
